coherent/cli/__main__.py
coherent/cli/__init__.py
coherent_cli-0.4.2.dist-info/METADATA
coherent_cli-0.4.2.dist-info/WHEEL
coherent_cli-0.4.2.dist-info/entry_points.txt
coherent_cli-0.4.2.dist-info/RECORD
