Metadata-Version: 2.3
Name: coherent.cli
Version: 0.4.2
Author-Email: "Jason R. Coombs" <jaraco@jaraco.com>
Summary: Command-line interface for Coherent Software Development System
Requires-Python: >= 3.9
Requires-Dist: coherent.test
Requires-Dist: typer
Requires-Dist: coherent.build
Requires-Dist: jaraco.vcs
Requires-Dist: jaraco.versioning
Provides-Extra: test
Provides-Extra: doc
Project-URL: Source, https://github.com/coherent-oss/coherent.cli
Classifier: Development Status :: 4 - Beta
Classifier: Intended Audience :: Developers
Classifier: License :: OSI Approved :: MIT License
Classifier: Programming Language :: Python :: 3
Classifier: Programming Language :: Python :: 3 :: Only
